{
    "@context": "https://linked.art/ns/v1/linked-art.json",
    "brought_into_existence_by": {
        "id": "http://data.museum.colby.edu/constituent/1506/birth",
        "timespan": {
            "begin_of_the_begin": "1867",
            "id": "http://data.museum.colby.edu/constituent/1506/birth/date",
            "type": "TimeSpan"
        },
        "type": "BeginningOfExistence"
    },
    "id": "http://data.museum.colby.edu/constituent/1506",
    "identified_by": [
        {
            "classified_as": [
                "aat:300404670"
            ],
            "id": "http://data.museum.colby.edu/constituent/1506/name",
            "includes": [
                {
                    "classified_as": [
                        "aat:300404651"
                    ],
                    "id": "http://data.museum.colby.edu/constituent/1506/first_name",
                    "type": "Name",
                    "value": "Bela Lyon"
                },
                {
                    "classified_as": [
                        "aat:300404652"
                    ],
                    "id": "http://data.museum.colby.edu/constituent/1506/last_name",
                    "type": "Name",
                    "value": "Pratt"
                }
            ],
            "type": "Name",
            "value": "Bela Lyon Pratt"
        },
        {
            "classified_as": [
                "aat:300404670"
            ],
            "id": "http://data.museum.colby.edu/constituent/1506/preferred_id",
            "type": "Identifier",
            "value": "1506"
        }
    ],
    "referred_to_by": [
        {
            "classified_as": [
                "aat:300080102"
            ],
            "id": "http://data.museum.colby.edu/constituent/1506/biography",
            "type": "LinguisticObject"
        }
    ],
    "skos:exactMatch": "500095555",
    "taken_out_of_existence_by": {
        "id": "http://data.museum.colby.edu/constituent/1506/death",
        "timespan": {
            "end_of_the_end": "1917",
            "id": "http://data.museum.colby.edu/constituent/1506/death/date",
            "type": "TimeSpan"
        },
        "type": "EndOfExistence"
    },
    "type": "Person"
}