{
    "@context": "https://linked.art/ns/v1/linked-art.json",
    "brought_into_existence_by": {
        "id": "http://data.museum.colby.edu/constituent/421/birth",
        "timespan": {
            "begin_of_the_begin": "1885",
            "id": "http://data.museum.colby.edu/constituent/421/birth/date",
            "type": "TimeSpan"
        },
        "type": "BeginningOfExistence"
    },
    "id": "http://data.museum.colby.edu/constituent/421",
    "identified_by": [
        {
            "classified_as": [
                "aat:300404670"
            ],
            "id": "http://data.museum.colby.edu/constituent/421/name",
            "includes": [
                {
                    "classified_as": [
                        "aat:300404651"
                    ],
                    "id": "http://data.museum.colby.edu/constituent/421/first_name",
                    "type": "Name",
                    "value": "Robert (-Victor-Felix)"
                },
                {
                    "classified_as": [
                        "aat:300404652"
                    ],
                    "id": "http://data.museum.colby.edu/constituent/421/last_name",
                    "type": "Name",
                    "value": "Delaunay"
                }
            ],
            "type": "Name",
            "value": "Robert (-Victor-Felix) Delaunay"
        },
        {
            "classified_as": [
                "aat:300404670"
            ],
            "id": "http://data.museum.colby.edu/constituent/421/preferred_id",
            "type": "Identifier",
            "value": "421"
        }
    ],
    "ore:isAggregatedBy": {
        "classified_as": [
            "aat:300379842"
        ],
        "id": "http://data.museum.colby.edu/thesauri/nationality/French",
        "label": "French",
        "type": "Aggregation"
    },
    "referred_to_by": [
        {
            "classified_as": [
                "aat:300080102"
            ],
            "id": "http://data.museum.colby.edu/constituent/421/biography",
            "type": "LinguisticObject"
        }
    ],
    "taken_out_of_existence_by": {
        "id": "http://data.museum.colby.edu/constituent/421/death",
        "timespan": {
            "end_of_the_end": "1941",
            "id": "http://data.museum.colby.edu/constituent/421/death/date",
            "type": "TimeSpan"
        },
        "type": "EndOfExistence"
    },
    "type": "Person"
}