{
    "@context": "https://linked.art/ns/v1/linked-art.json",
    "brought_into_existence_by": {
        "id": "http://data.museum.colby.edu/constituent/964/birth",
        "timespan": {
            "begin_of_the_begin": "1922",
            "id": "http://data.museum.colby.edu/constituent/964/birth/date",
            "type": "TimeSpan"
        },
        "type": "BeginningOfExistence"
    },
    "id": "http://data.museum.colby.edu/constituent/964",
    "identified_by": [
        {
            "classified_as": [
                "aat:300404670"
            ],
            "id": "http://data.museum.colby.edu/constituent/964/name",
            "includes": [
                {
                    "classified_as": [
                        "aat:300404651"
                    ],
                    "id": "http://data.museum.colby.edu/constituent/964/first_name",
                    "type": "Name",
                    "value": "Jan"
                },
                {
                    "classified_as": [
                        "aat:300404652"
                    ],
                    "id": "http://data.museum.colby.edu/constituent/964/last_name",
                    "type": "Name",
                    "value": "M&#252;ller"
                }
            ],
            "type": "Name",
            "value": "Jan M&#252;ller"
        },
        {
            "classified_as": [
                "aat:300404670"
            ],
            "id": "http://data.museum.colby.edu/constituent/964/preferred_id",
            "type": "Identifier",
            "value": "964"
        }
    ],
    "referred_to_by": [
        {
            "classified_as": [
                "aat:300080102"
            ],
            "id": "http://data.museum.colby.edu/constituent/964/biography",
            "type": "LinguisticObject"
        }
    ],
    "skos:exactMatch": "500001212",
    "taken_out_of_existence_by": {
        "id": "http://data.museum.colby.edu/constituent/964/death",
        "timespan": {
            "end_of_the_end": "1958",
            "id": "http://data.museum.colby.edu/constituent/964/death/date",
            "type": "TimeSpan"
        },
        "type": "EndOfExistence"
    },
    "type": "Person"
}